MythosMaker/__init__.py
MythosMaker/app/__init__.py
MythosMaker/app/database.py
MythosMaker/generation/__init__.py
MythosMaker/generation/create_fake_data.py
MythosMaker/generation/create_persist_all.py
MythosMaker/generation/run_fake_generator.py
MythosMaker/utils/__init__.py
MythosMaker/utils/record_keeper.py
MythosMaker-0.0.5.dist-info/LICENSE
MythosMaker-0.0.5.dist-info/METADATA
MythosMaker-0.0.5.dist-info/WHEEL
MythosMaker-0.0.5.dist-info/top_level.txt
MythosMaker-0.0.5.dist-info/RECORD
