Metadata-Version: 2.1
Name: MythosMaker
Version: 0.0.5
Summary: A simple package to persist fake data objects into a relational database
Home-page: https://github.com/Ryan-Comerford/Fake-Data-Generator
Author: Ryan Comerford
Author-email: Ryan Comerford <comerford.ryan31@gmail.com>
Project-URL: Homepage, https://github.com/Ryan-Comerford/Fake-Data-Generator
Project-URL: Issues, https://github.com/Ryan-Comerford/Fake-Data-Generator/issues
Classifier: Programming Language :: Python :: 3
Classifier: License :: OSI Approved :: MIT License
Classifier: Operating System :: OS Independent
Requires-Python: >=3.8
License-File: LICENSE
